{"name":"김태환","code":"PMU9608V","nameCH":"金泰煥","nameEN":"KIM Tae-whan","birthdayType":"음","birthday":"1943-09-24","pictureURL":"https://www.assembly.go.kr/static/portal/img/openassm/PMU9608V.jpg","career":{"reElectName":"3선","ages":{"17":{"age":17,"party":"한나라당","localName":"경북 구미시을","record":{"Age":"제17대","Code":"PMU9608V","Name":"김태환","NameCH":"金泰煥","PoliticalParty":"한나라당","LocalName":"경북 구미시을","발의수(전체)":404,"발의수(대표발의)":8,"발의수(공동발의)":396,"원안가결(전체)":11,"수정가결(전체)":47,"철회(전체)":4,"부결(전체)":0,"수정안반영폐기(전체)":0,"대안반영폐기(전체)":106,"폐기(전체)":20,"임기만료폐기(전체)":216,"회기불계속폐기(전체)":0,"기타(전체)":0,"원안가결(대표발의)":0,"수정가결(대표발의)":2,"철회(대표발의)":0,"부결(대표발의)":0,"수정안반영폐기(대표발의)":0,"대안반영폐기(대표발의)":3,"폐기(대표발의)":1,"임기만료폐기(대표발의)":2,"회기불계속폐기(대표발의)":0,"기타":0,"원안가결(공동발의)":11,"수정가결(공동발의)":45,"철회(공동발의)":4,"부결(공동발의)":0,"수정안반영폐기(공동발의)":0,"대안반영폐기(공동발의)":103,"폐기(공동발의)":19,"임기만료폐기(공동발의)":214,"회기불계속폐기(공동발의)":0,"기타(공동발의)":0},"representativeBillIds":["PRC_R0C7U1D1X0C9D1W6N0Y4X1F1S1E9S7","038133","034543","033428","033427","029674","028226","028153"]},"18":{"age":18,"party":"무소속","localName":"경북 구미시을","record":{"Age":"제18대","Code":"PMU9608V","Name":"김태환","NameCH":"金泰煥","PoliticalParty":"무소속","LocalName":"경북 구미시을","발의수(전체)":322,"발의수(대표발의)":10,"발의수(공동발의)":312,"원안가결(전체)":4,"수정가결(전체)":29,"철회(전체)":6,"부결(전체)":0,"수정안반영폐기(전체)":0,"대안반영폐기(전체)":107,"폐기(전체)":21,"임기만료폐기(전체)":155,"회기불계속폐기(전체)":0,"기타(전체)":0,"원안가결(대표발의)":0,"수정가결(대표발의)":4,"철회(대표발의)":0,"부결(대표발의)":0,"수정안반영폐기(대표발의)":0,"대안반영폐기(대표발의)":2,"폐기(대표발의)":1,"임기만료폐기(대표발의)":3,"회기불계속폐기(대표발의)":0,"기타":0,"원안가결(공동발의)":4,"수정가결(공동발의)":25,"철회(공동발의)":6,"부결(공동발의)":0,"수정안반영폐기(공동발의)":0,"대안반영폐기(공동발의)":105,"폐기(공동발의)":20,"임기만료폐기(공동발의)":152,"회기불계속폐기(공동발의)":0,"기타(공동발의)":0},"representativeBillIds":["PRC_J1L1X1S0B1T9V1P5F0S7C2D9I0V6W3","PRC_L1E1Y0K6D1T0V1H1D4H1E1O5R5P5S2","PRC_D1W1O0A6Z1S0L1U1F3T4H0F3D8Z1T6","PRC_U1H1M0X1Z1H4X1V6J0S5K2B3Q9T0B9","PRC_H0D9L1R2Q2B4Z1B0Z5G7H2R7B3N9X9","PRC_Y0Q9L1Y2B0F7G1C1Q5P7U0P9S6O0R8","PRC_A0W8N1L2B2B3I1T5E3X9M2R1H7A3M9","PRC_H0E8W1U2Q2E3Y1W5L3J7U1Y3R5U8I8","PRC_W0D8Y1W2W1H9D1C3X5J6R2Q4G5G9V8","PRC_C0I8D0F7D1A8T1I6T1E1R3H6C3R6M9"]},"19":{"age":19,"party":"새누리당","localName":"경북 구미시을","record":{"Age":"제19대","Code":"PMU9608V","Name":"김태환","NameCH":"金泰煥","PoliticalParty":"새누리당","LocalName":"경북 구미시을","발의수(전체)":411,"발의수(대표발의)":14,"발의수(공동발의)":397,"원안가결(전체)":11,"수정가결(전체)":64,"철회(전체)":3,"부결(전체)":0,"수정안반영폐기(전체)":0,"대안반영폐기(전체)":123,"폐기(전체)":8,"임기만료폐기(전체)":202,"회기불계속폐기(전체)":0,"기타(전체)":0,"원안가결(대표발의)":0,"수정가결(대표발의)":2,"철회(대표발의)":0,"부결(대표발의)":0,"수정안반영폐기(대표발의)":0,"대안반영폐기(대표발의)":4,"폐기(대표발의)":0,"임기만료폐기(대표발의)":8,"회기불계속폐기(대표발의)":0,"기타":0,"원안가결(공동발의)":11,"수정가결(공동발의)":62,"철회(공동발의)":3,"부결(공동발의)":0,"수정안반영폐기(공동발의)":0,"대안반영폐기(공동발의)":119,"폐기(공동발의)":8,"임기만료폐기(공동발의)":194,"회기불계속폐기(공동발의)":0,"기타(공동발의)":0},"representativeBillIds":["PRC_J1W5B1B2X0O8E1Z3P1K4Q3Z5I9I0Z0","PRC_T1U5R1F2T0F8O1P1J2U1Q3L7X8O8E3","PRC_V1U5L1M2K0E8C1T1B1P7X4G2X9B4X8","PRC_Y1G5N1E2M0L8X1B1I1X6U0N9G6J3X9","PRC_W1N5G1N2I0Y8A1J1M1T5R3N3A0U4A2","PRC_P1D5N1I2W0Y8L1H1S1K3N0B1M8E8Q8","PRC_I1X5E0Y2I2J5N1V1J2E2G5Q0Z2Q0V0","PRC_O1E4I0I9C3L0C1M4V1M6X3Q6R3M3D3","PRC_E1S3B1U0O0T2Z1H1U3M9U0E4V0Y4B5","PRC_F1P3L0H5L3F1H1U1V3P3T2O1S3E2V9","PRC_M1Y3K0H4H0X9F1C7H1L0N2S1H5U4X8","PRC_Z1K3O0Y3B1T1W1G7Q5W9V4J0X2W2N3","PRC_N1Q3Q0R3J1J1B1E7A2Z9E1I4Z5W1Y7","PRC_S1T2L0D7I0V3K1P1R2W9I3F6H3Z2P7"]}},"belongCommittee":["과학기술정보통신위원회","예산결산특별위원회","일자리창출을위한특별위원회","건설교통위원회/기후변화대응·녹색성장특별위원회","예산결산특별위원회","일자리창출 및 중소기업경쟁력특별위원회","지식경제위원회/정무위원회","안전행정위원회","행정안전위원회"]}}