{"name":"박재완","code":"JPE16970","nameCH":"朴宰完","nameEN":"Bahk, Jae-wan","birthdayType":"음","birthday":"1955-01-24","pictureURL":"https://www.assembly.go.kr/static/portal/img/openassm/JPE16970.jpg","career":{"reElectName":"초선","ages":{"17":{"age":17,"party":"한나라당","localName":"비례대표","record":{"Age":"제17대","Code":"JPE16970","Name":"박재완","NameCH":"朴宰完","PoliticalParty":"한나라당","LocalName":"비례대표","발의수(전체)":1108,"발의수(대표발의)":76,"발의수(공동발의)":1032,"원안가결(전체)":30,"수정가결(전체)":95,"철회(전체)":20,"부결(전체)":0,"수정안반영폐기(전체)":0,"대안반영폐기(전체)":313,"폐기(전체)":92,"임기만료폐기(전체)":558,"회기불계속폐기(전체)":0,"기타(전체)":0,"원안가결(대표발의)":1,"수정가결(대표발의)":0,"철회(대표발의)":3,"부결(대표발의)":0,"수정안반영폐기(대표발의)":0,"대안반영폐기(대표발의)":15,"폐기(대표발의)":9,"임기만료폐기(대표발의)":48,"회기불계속폐기(대표발의)":0,"기타":0,"원안가결(공동발의)":29,"수정가결(공동발의)":95,"철회(공동발의)":17,"부결(공동발의)":0,"수정안반영폐기(공동발의)":0,"대안반영폐기(공동발의)":298,"폐기(공동발의)":83,"임기만료폐기(공동발의)":510,"회기불계속폐기(공동발의)":0,"기타(공동발의)":0},"representativeBillIds":["PRC_U0W8G0Z1J2L8V1H7A2C5M0W8H7C9T0","PRC_K0Y7D1F1G1D6X1Q5R5C6D3Z3F7K6I6","PRC_Q0N7H1V1C1O6K1W5F1S7U1D0T5F0U4","PRC_H0Z7T0U9G1X2R1Z0N2Y1U2S7W4L1T1","PRC_G0G7S0E9W1U0X1B4T5Q6D0E2T8G9H9","PRC_R0X7G0T5Y3V0J1R8O5G8B3P7Q1R1H4","PRC_G0R7J0K5R3C0W1A8X5V4W5Z1F0N9W3","PRC_X0C7E0H4R2F6D1Y0E5T2L3M1J1V9Y3","PRC_S0Z7M0Y2H1X5Q1X6Q1A2V1Y3K7G8E9","PRC_A0O7M0O1Z3I0N1O8K1X2X2R3B4S0P1","PRC_H0N7J0C1E2R4U1A6U3B5B2X9Y2P2S2","PRC_Y0A7Y0B1K2M4Y1F6E3H4G3U8E5P0B7","PRC_N0J6H1U2O2N9D1A0G1R3B2F1D2W3X7","036816","036815","036814","036813","036064","036063","036062","035058","035056","035054","035052","035050","034825","033130","033129","032871","032495","032328","032327","032234","032233","032166","032165","032164","032163","032125","031826","031825","031824","031597","031596","031582","031571","031570","030374","030334","030279","030278","030277","030276","030275","030274","030273","030271","030249","030248","030247","030144","030143","030142","030141","029679","029678","029475","029474","029434","028609","028515","028514","028400","028399","028398","028287"]}},"belongCommittee":["국민연금제도개선특별위원회","투명사회협약실천특별위원회","보건복지위원회","법제사법위원회","국회개혁특별위원회","산업자원위원회","예산결산특별위원회"]}}