{"name":"윤경식","code":"X4S23695","nameCH":"尹景湜","nameEN":"Yoon Kyeong-sig","birthdayType":"음","birthday":"1962-03-20","pictureURL":"https://www.assembly.go.kr/static/portal/img/openassm/X4S23695.jpg","career":{"reElectName":"초선","ages":{"16":{"age":16,"party":"한나라당","localName":"충북 청주시흥덕구","record":{"Age":"제16대","Code":"X4S23695","Name":"윤경식","NameCH":"尹景湜","PoliticalParty":"한나라당","LocalName":"충북 청주시흥덕구","발의수(전체)":335,"발의수(대표발의)":8,"발의수(공동발의)":327,"원안가결(전체)":9,"수정가결(전체)":42,"철회(전체)":4,"부결(전체)":1,"수정안반영폐기(전체)":0,"대안반영폐기(전체)":89,"폐기(전체)":30,"임기만료폐기(전체)":160,"회기불계속폐기(전체)":0,"기타(전체)":0,"원안가결(대표발의)":0,"수정가결(대표발의)":1,"철회(대표발의)":0,"부결(대표발의)":0,"수정안반영폐기(대표발의)":0,"대안반영폐기(대표발의)":3,"폐기(대표발의)":0,"임기만료폐기(대표발의)":4,"회기불계속폐기(대표발의)":0,"기타":0,"원안가결(공동발의)":9,"수정가결(공동발의)":41,"철회(공동발의)":4,"부결(공동발의)":1,"수정안반영폐기(공동발의)":0,"대안반영폐기(공동발의)":86,"폐기(공동발의)":30,"임기만료폐기(공동발의)":156,"회기불계속폐기(공동발의)":0,"기타(공동발의)":0},"representativeBillIds":["025383","025025","024552","024166","023943","023486","020640","016867"]}},"belongCommittee":["감사원장(윤성식)임명동의에관한인사청문특별위원회","국무총리후보자(고건)에관한인사청문특별위원회","2010년평창동계올림픽유치특별위원회","행정자치위원회","교육위원회","예산결산특별위원회","문화관광위원회","통일외교통상위원회","한빛은행대출관련의혹사건등의진상조사를위한국정조사특별위원회","인사청문특별위원회(대법관)","국회운영위원회","법제사법위원회","윤리특별위원회","국회상임위원회위원정수에관한규칙개정특별위원회"]}}